videpy
