Metadata-Version: 2.1
Name: videpy
Version: 0.0.5
Summary: Tools to handle samples posteriori from Stan (pystan)
Home-page: https://github.com/rodolpho-progmatica/videpy
Author: Rodolpho Macedo dos Santos
Author-email: rodolpho.ime@gmail.com
License: MIT License
Keywords: videpy,vide,bayesian,stan,pystan,rethinking
Platform: UNKNOWN
